{
 "name": "Shakira","children": [
  {"name": "hijo" },
  {"name": "hijo2" },
  {"name": "pareja" },

  {

   "name": "PAIS2","children": [
    {"name": "PALABRA1" },
    {"name": "PALABRA2" },

    {
     "name": "PAIS3","children": [
      {"name": "Shakira" },
      {"name": "Shakira" },
      {"name": "Paola" }
     ]
    },
    {
     "name": "PAISSSS","children": [
      {"name": "a" },
      {"name": "b" },
      {"name": "a" }
     ]
    },
    {
    "name": "(u'Albert Schweitzer'",
    "[u'1815|12|10'": "[u'1875|01|14'",
    "u'England\\n '])": "u'France'])"
   },
    {
     "name": "PAIS5",
     "children": [
      {"name": "f"}

     ]
    }
   ]
  },
  {"name": "DOSre" }
 ]
}